dbt/__init__.py
dbt/adapters/__init__.py
dbt/adapters/netezza/__init__.py
dbt/adapters/netezza/__version__.py
dbt/adapters/netezza/column.py
dbt/adapters/netezza/connections.py
dbt/adapters/netezza/et_options_parser.py
dbt/adapters/netezza/impl.py
dbt/adapters/netezza/relation.py
dbt/include/__init__.py
dbt/include/netezza/__init__.py
dbt/include/netezza/dbt_project.yml
dbt/include/netezza/profile_template.yml
dbt/include/netezza/macros/adapters.sql
dbt/include/netezza/macros/catalog.sql
dbt/include/netezza/macros/grants.sql
dbt/include/netezza/macros/schema.sql
dbt/include/netezza/macros/materializations/incremental_strategies.sql
dbt/include/netezza/macros/materializations/merge.sql
dbt/include/netezza/macros/materializations/seed.sql
dbt/include/netezza/macros/materializations/snapshot.sql
dbt/include/netezza/macros/utils/array_append.sql
dbt/include/netezza/macros/utils/array_concat.sql
dbt/include/netezza/macros/utils/array_construct.sql
dbt/include/netezza/macros/utils/bool_or.sql
dbt/include/netezza/macros/utils/cast_bool_to_text.sql
dbt/include/netezza/macros/utils/concat.sql
dbt/include/netezza/macros/utils/dateadd.sql
dbt/include/netezza/macros/utils/datediff.sql
dbt/include/netezza/macros/utils/hash.sql
dbt/include/netezza/macros/utils/lastday.sql
dbt/include/netezza/macros/utils/listagg.sql
dbt/include/netezza/macros/utils/right.sql
dbt/include/netezza/macros/utils/split_part.sql
dbt/include/netezza/macros/utils/timestamps.sql
dbt_ibm_netezza-1.0.6.dist-info/licenses/LICENSE
dbt_ibm_netezza-1.0.6.dist-info/licenses/LICENSE copy
dbt_ibm_netezza-1.0.6.dist-info/METADATA
dbt_ibm_netezza-1.0.6.dist-info/WHEEL
dbt_ibm_netezza-1.0.6.dist-info/top_level.txt
dbt_ibm_netezza-1.0.6.dist-info/RECORD
