Metadata-Version: 2.4
Name: dbt-ibm-netezza
Version: 1.0.6
Summary: The Netezza adapter plugin for dbt
Home-page: https://github.com/IBM/nz-dbt
Author: Abhishek Jog
Author-email: abhishekjog@gmail.com
Classifier: Operating System :: Microsoft :: Windows
Classifier: Operating System :: MacOS :: MacOS X
Classifier: Operating System :: POSIX :: Linux
Classifier: Programming Language :: Python :: 3.9
Classifier: Programming Language :: Python :: 3.10
Requires-Python: >=3.9
License-File: LICENSE
License-File: LICENSE copy
Requires-Dist: dbt-core==1.9.2
Requires-Dist: nzpy==1.15
Dynamic: author
Dynamic: author-email
Dynamic: classifier
Dynamic: description
Dynamic: description-content-type
Dynamic: home-page
Dynamic: license-file
Dynamic: requires-dist
Dynamic: requires-python
Dynamic: summary
